protomate/__init__.py
protomate/languages.py
protomate/script.py
protomate/settings.py
protomate/utils.py
protomate-1.0.3.dist-info/entry_points.txt
protomate-1.0.3.dist-info/WHEEL
protomate-1.0.3.dist-info/METADATA
protomate-1.0.3.dist-info/RECORD
