Metadata-Version: 2.1
Name: protomate
Version: 1.0.3
Summary: Python built CLI tool for automated github project initialization.
Home-page: https://github.com/rednafi/protomate
License: MIT
Author: Redowan Delowar
Requires-Python: >=3.7,<4.0
Classifier: License :: OSI Approved :: MIT License
Classifier: Programming Language :: Python
Classifier: Programming Language :: Python :: 3
Classifier: Programming Language :: Python :: 3.7
Classifier: Programming Language :: Python :: 3.8
Classifier: Programming Language :: Python :: Implementation :: CPython
Classifier: Programming Language :: Python :: Implementation :: PyPy
Requires-Dist: PyGithub (==1.44.1)
Requires-Dist: art (==4.4)
Requires-Dist: click (>=7.0,<8.0)
Requires-Dist: colorama (==0.4.3)
Requires-Dist: sty (==1.0.0b12)
Requires-Dist: termcolor (==1.1.0)
Project-URL: Documentation, https://rednafi.github.io/protomate/
Project-URL: Repository, https://github.com/rednafi/protomate
